{"2007":{"race-results":[{"race-name":"Australia","winner":"Kimi Räikkönen","winner-car":"Ferrari","date":"18/3/2007","laps":58,"final-grid":[{"position":"1","car-driven":"Ferrari","drivers-number":"6","drivers-name":"Kimi Räikkönen","laps":"58","final-time":"1:25:28.770","points-earned":"10","race":"Australia"},{"position":"2","car-driven":"McLaren Mercedes","drivers-number":"1","drivers-name":"Fernando Alonso","laps":"58","final-time":"+7.242s","points-earned":"8"},{"position":"3","car-driven":"McLaren Mercedes","drivers-number":"2","drivers-name":"Lewis Hamilton","laps":"58","final-time":"+18.595s","points-earned":"6"},{"position":"4","car-driven":"Sauber BMW","drivers-number":"9","drivers-name":"Nick Heidfeld","laps":"58","final-time":"+38.763s","points-earned":"5"},{"position":"5","car-driven":"Renault","drivers-number":"3","drivers-name":"Giancarlo Fisichella","laps":"58","final-time":"+66.469s","points-earned":"4"},{"position":"6","car-driven":"Ferrari","drivers-number":"5","drivers-name":"Felipe Massa","laps":"58","final-time":"+66.805s","points-earned":"3"},{"position":"7","car-driven":"Williams Toyota","drivers-number":"16","drivers-name":"Nico Rosberg","laps":"57","final-time":"+1 lap","points-earned":"2"},{"position":"8","car-driven":"Toyota","drivers-number":"11","drivers-name":"Ralf Schumacher","laps":"57","final-time":"+1 lap","points-earned":"1"},{"position":"9","car-driven":"Toyota","drivers-number":"12","drivers-name":"Jarno Trulli","laps":"57","final-time":"+1 lap","points-earned":"0"},{"position":"10","car-driven":"Renault","drivers-number":"4","drivers-name":"Heikki Kovalainen","laps":"57","final-time":"+1 lap","points-earned":"0"},{"position":"11","car-driven":"Honda","drivers-number":"8","drivers-name":"Rubens Barrichello","laps":"57","final-time":"+1 lap","points-earned":"0"},{"position":"12","car-driven":"Super Aguri Honda","drivers-number":"22","drivers-name":"Takuma Sato","laps":"57","final-time":"+1 lap","points-earned":"0"},{"position":"13","car-driven":"Red Bull Renault","drivers-number":"15","drivers-name":"Mark Webber","laps":"57","final-time":"+1 lap","points-earned":"0"},{"position":"14","car-driven":"STR Ferrari","drivers-number":"18","drivers-name":"Vitantonio Liuzzi","laps":"57","final-time":"+1 lap","points-earned":"0"},{"position":"15","car-driven":"Honda","drivers-number":"7","drivers-name":"Jenson Button","laps":"57","final-time":"+1 lap","points-earned":"0"},{"position":"16","car-driven":"Super Aguri Honda","drivers-number":"23","drivers-name":"Anthony Davidson","laps":"56","final-time":"+2 laps","points-earned":"0"},{"position":"17","car-driven":"Spyker Ferrari","drivers-number":"20","drivers-name":"Adrian Sutil","laps":"56","final-time":"+2 laps","points-earned":"0"},{"position":"NC","car-driven":"Williams Toyota","drivers-number":"17","drivers-name":"Alexander Wurz","laps":"48","final-time":"DNF","points-earned":"0"},{"position":"NC","car-driven":"Red Bull Renault","drivers-number":"14","drivers-name":"David Coulthard","laps":"48","final-time":"DNF","points-earned":"0"},{"position":"NC","car-driven":"Sauber BMW","drivers-number":"10","drivers-name":"Robert Kubica","laps":"36","final-time":"DNF","points-earned":"0"},{"position":"NC","car-driven":"STR Ferrari","drivers-number":"19","drivers-name":"Scott Speed","laps":"28","final-time":"DNF","points-earned":"0"},{"position":"NC","car-driven":"Spyker Ferrari","drivers-number":"21","drivers-name":"Christijan Albers","laps":"10","final-time":"DNF","points-earned":"0"}]},{"race-name":"Malaysia","winner":"Fernando Alonso","winner-car":"McLaren Mercedes","date":"8/4/2007","laps":56,"final-grid":[{"position":"1","car-driven":"McLaren Mercedes","drivers-number":"1","drivers-name":"Fernando Alonso","laps":"56","final-time":"1:32:14.930","points-earned":"10","race":"Malaysia"},{"position":"2","car-driven":"McLaren Mercedes","drivers-number":"2","drivers-name":"Lewis Hamilton","laps":"56","final-time":"+17.557s","points-earned":"8"},{"position":"3","car-driven":"Ferrari","drivers-number":"6","drivers-name":"Kimi Räikkönen","laps":"56","final-time":"+18.339s","points-earned":"6"},{"position":"4","car-driven":"Sauber BMW","drivers-number":"9","drivers-name":"Nick Heidfeld","laps":"56","final-time":"+33.777s","points-earned":"5"},{"position":"5","car-driven":"Ferrari","drivers-number":"5","drivers-name":"Felipe Massa","laps":"56","final-time":"+36.705s","points-earned":"4"},{"position":"6","car-driven":"Renault","drivers-number":"3","drivers-name":"Giancarlo Fisichella","laps":"56","final-time":"+65.638s","points-earned":"3"},{"position":"7","car-driven":"Toyota","drivers-number":"12","drivers-name":"Jarno Trulli","laps":"56","final-time":"+70.132s","points-earned":"2"},{"position":"8","car-driven":"Renault","drivers-number":"4","drivers-name":"Heikki Kovalainen","laps":"56","final-time":"+72.015s","points-earned":"1"},{"position":"9","car-driven":"Williams Toyota","drivers-number":"17","drivers-name":"Alexander Wurz","laps":"56","final-time":"+89.924s","points-earned":"0"},{"position":"10","car-driven":"Red Bull Renault","drivers-number":"15","drivers-name":"Mark Webber","laps":"56","final-time":"+93.556s","points-earned":"0"},{"position":"11","car-driven":"Honda","drivers-number":"8","drivers-name":"Rubens Barrichello","laps":"55","final-time":"+1 lap","points-earned":"0"},{"position":"12","car-driven":"Honda","drivers-number":"7","drivers-name":"Jenson Button","laps":"55","final-time":"+1 lap","points-earned":"0"},{"position":"13","car-driven":"Super Aguri Honda","drivers-number":"22","drivers-name":"Takuma Sato","laps":"55","final-time":"+1 lap","points-earned":"0"},{"position":"14","car-driven":"STR Ferrari","drivers-number":"19","drivers-name":"Scott Speed","laps":"55","final-time":"+1 lap","points-earned":"0"},{"position":"15","car-driven":"Toyota","drivers-number":"11","drivers-name":"Ralf Schumacher","laps":"55","final-time":"+1 lap","points-earned":"0"},{"position":"16","car-driven":"Super Aguri Honda","drivers-number":"23","drivers-name":"Anthony Davidson","laps":"55","final-time":"+1 lap","points-earned":"0"},{"position":"17","car-driven":"STR Ferrari","drivers-number":"18","drivers-name":"Vitantonio Liuzzi","laps":"55","final-time":"+1 lap","points-earned":"0"},{"position":"18","car-driven":"Sauber BMW","drivers-number":"10","drivers-name":"Robert Kubica","laps":"55","final-time":"+1 lap","points-earned":"0"},{"position":"NC","car-driven":"Williams Toyota","drivers-number":"16","drivers-name":"Nico Rosberg","laps":"42","final-time":"DNF","points-earned":"0"},{"position":"NC","car-driven":"Red Bull Renault","drivers-number":"14","drivers-name":"David Coulthard","laps":"36","final-time":"DNF","points-earned":"0"},{"position":"NC","car-driven":"Spyker Ferrari","drivers-number":"21","drivers-name":"Christijan Albers","laps":"7","final-time":"DNF","points-earned":"0"},{"position":"NC","car-driven":"Spyker Ferrari","drivers-number":"20","drivers-name":"Adrian Sutil","laps":"0","final-time":"DNF","points-earned":"0"}]},{"race-name":"Bahrain","winner":"Felipe Massa","winner-car":"Ferrari","date":"15/4/2007","laps":57,"final-grid":[{"position":"1","car-driven":"Ferrari","drivers-number":"5","drivers-name":"Felipe Massa","laps":"57","final-time":"1:33:27.515","points-earned":"10","race":"Bahrain"},{"position":"2","car-driven":"McLaren Mercedes","drivers-number":"2","drivers-name":"Lewis Hamilton","laps":"57","final-time":"+2.360s","points-earned":"8"},{"position":"3","car-driven":"Ferrari","drivers-number":"6","drivers-name":"Kimi Räikkönen","laps":"57","final-time":"+10.839s","points-earned":"6"},{"position":"4","car-driven":"Sauber BMW","drivers-number":"9","drivers-name":"Nick Heidfeld","laps":"57","final-time":"+13.831s","points-earned":"5"},{"position":"5","car-driven":"McLaren Mercedes","drivers-number":"1","drivers-name":"Fernando Alonso","laps":"57","final-time":"+14.426s","points-earned":"4"},{"position":"6","car-driven":"Sauber BMW","drivers-number":"10","drivers-name":"Robert Kubica","laps":"57","final-time":"+45.529s","points-earned":"3"},{"position":"7","car-driven":"Toyota","drivers-number":"12","drivers-name":"Jarno Trulli","laps":"57","final-time":"+81.371s","points-earned":"2"},{"position":"8","car-driven":"Renault","drivers-number":"3","drivers-name":"Giancarlo Fisichella","laps":"57","final-time":"+81.701s","points-earned":"1"},{"position":"9","car-driven":"Renault","drivers-number":"4","drivers-name":"Heikki Kovalainen","laps":"57","final-time":"+89.411s","points-earned":"0"},{"position":"10","car-driven":"Williams Toyota","drivers-number":"16","drivers-name":"Nico Rosberg","laps":"57","final-time":"+89.916s","points-earned":"0"},{"position":"11","car-driven":"Williams Toyota","drivers-number":"17","drivers-name":"Alexander Wurz","laps":"56","final-time":"+1 lap","points-earned":"0"},{"position":"12","car-driven":"Toyota","drivers-number":"11","drivers-name":"Ralf Schumacher","laps":"56","final-time":"+1 lap","points-earned":"0"},{"position":"13","car-driven":"Honda","drivers-number":"8","drivers-name":"Rubens Barrichello","laps":"56","final-time":"+1 lap","points-earned":"0"},{"position":"14","car-driven":"Spyker Ferrari","drivers-number":"21","drivers-name":"Christijan Albers","laps":"55","final-time":"+2 laps","points-earned":"0"},{"position":"15","car-driven":"Spyker Ferrari","drivers-number":"20","drivers-name":"Adrian Sutil","laps":"53","final-time":"+4 laps","points-earned":"0"},{"position":"16","car-driven":"Super Aguri Honda","drivers-number":"23","drivers-name":"Anthony Davidson","laps":"51","final-time":"DNF","points-earned":"0"},{"position":"NC","car-driven":"Red Bull Renault","drivers-number":"15","drivers-name":"Mark Webber","laps":"41","final-time":"DNF","points-earned":"0"},{"position":"NC","car-driven":"Red Bull Renault","drivers-number":"14","drivers-name":"David Coulthard","laps":"36","final-time":"DNF","points-earned":"0"},{"position":"NC","car-driven":"Super Aguri Honda","drivers-number":"22","drivers-name":"Takuma Sato","laps":"34","final-time":"DNF","points-earned":"0"},{"position":"NC","car-driven":"STR Ferrari","drivers-number":"18","drivers-name":"Vitantonio Liuzzi","laps":"26","final-time":"DNF","points-earned":"0"},{"position":"NC","car-driven":"Honda","drivers-number":"7","drivers-name":"Jenson Button","laps":"0","final-time":"DNF","points-earned":"0"},{"position":"NC","car-driven":"STR Ferrari","drivers-number":"19","drivers-name":"Scott Speed","laps":"0","final-time":"DNF","points-earned":"0"}]},{"race-name":"Spain","winner":"Felipe Massa","winner-car":"Ferrari","date":"13/5/2007","laps":65,"final-grid":[{"position":"1","car-driven":"Ferrari","drivers-number":"5","drivers-name":"Felipe Massa","laps":"65","final-time":"1:31:36.230","points-earned":"10","race":"Spain"},{"position":"2","car-driven":"McLaren Mercedes","drivers-number":"2","drivers-name":"Lewis Hamilton","laps":"65","final-time":"+6.790s","points-earned":"8"},{"position":"3","car-driven":"McLaren Mercedes","drivers-number":"1","drivers-name":"Fernando Alonso","laps":"65","final-time":"+17.456s","points-earned":"6"},{"position":"4","car-driven":"Sauber BMW","drivers-number":"10","drivers-name":"Robert Kubica","laps":"65","final-time":"+31.615s","points-earned":"5"},{"position":"5","car-driven":"Red Bull Renault","drivers-number":"14","drivers-name":"David Coulthard","laps":"65","final-time":"+58.331s","points-earned":"4"},{"position":"6","car-driven":"Williams Toyota","drivers-number":"16","drivers-name":"Nico Rosberg","laps":"65","final-time":"+59.538s","points-earned":"3"},{"position":"7","car-driven":"Renault","drivers-number":"4","drivers-name":"Heikki Kovalainen","laps":"65","final-time":"+62.128s","points-earned":"2"},{"position":"8","car-driven":"Super Aguri Honda","drivers-number":"22","drivers-name":"Takuma Sato","laps":"64","final-time":"+1 lap","points-earned":"1"},{"position":"9","car-driven":"Renault","drivers-number":"3","drivers-name":"Giancarlo Fisichella","laps":"64","final-time":"+1 lap","points-earned":"0"},{"position":"10","car-driven":"Honda","drivers-number":"8","drivers-name":"Rubens Barrichello","laps":"64","final-time":"+1 lap","points-earned":"0"},{"position":"11","car-driven":"Super Aguri Honda","drivers-number":"23","drivers-name":"Anthony Davidson","laps":"64","final-time":"+1 lap","points-earned":"0"},{"position":"12","car-driven":"Honda","drivers-number":"7","drivers-name":"Jenson Button","laps":"64","final-time":"+1 lap","points-earned":"0"},{"position":"13","car-driven":"Spyker Ferrari","drivers-number":"20","drivers-name":"Adrian Sutil","laps":"63","final-time":"+2 laps","points-earned":"0"},{"position":"14","car-driven":"Spyker Ferrari","drivers-number":"21","drivers-name":"Christijan Albers","laps":"63","final-time":"+2 laps","points-earned":"0"},{"position":"NC","car-driven":"Sauber BMW","drivers-number":"9","drivers-name":"Nick Heidfeld","laps":"46","final-time":"DNF","points-earned":"0"},{"position":"NC","car-driven":"Toyota","drivers-number":"11","drivers-name":"Ralf Schumacher","laps":"44","final-time":"DNF","points-earned":"0"},{"position":"NC","car-driven":"STR Ferrari","drivers-number":"18","drivers-name":"Vitantonio Liuzzi","laps":"19","final-time":"DNF","points-earned":"0"},{"position":"NC","car-driven":"STR Ferrari","drivers-number":"19","drivers-name":"Scott Speed","laps":"9","final-time":"DNF","points-earned":"0"},{"position":"NC","car-driven":"Ferrari","drivers-number":"6","drivers-name":"Kimi Räikkönen","laps":"9","final-time":"DNF","points-earned":"0"},{"position":"NC","car-driven":"Toyota","drivers-number":"12","drivers-name":"Jarno Trulli","laps":"8","final-time":"DNF","points-earned":"0"},{"position":"NC","car-driven":"Red Bull Renault","drivers-number":"15","drivers-name":"Mark Webber","laps":"7","final-time":"DNF","points-earned":"0"},{"position":"NC","car-driven":"Williams Toyota","drivers-number":"17","drivers-name":"Alexander Wurz","laps":"1","final-time":"DNF","points-earned":"0"}]},{"race-name":"Monaco","winner":"Fernando Alonso","winner-car":"McLaren Mercedes","date":"27/5/2007","laps":78,"final-grid":[{"position":"1","car-driven":"McLaren Mercedes","drivers-number":"1","drivers-name":"Fernando Alonso","laps":"78","final-time":"1:40:29.329","points-earned":"10","race":"Monaco"},{"position":"2","car-driven":"McLaren Mercedes","drivers-number":"2","drivers-name":"Lewis Hamilton","laps":"78","final-time":"+4.095s","points-earned":"8"},{"position":"3","car-driven":"Ferrari","drivers-number":"5","drivers-name":"Felipe Massa","laps":"78","final-time":"+69.114s","points-earned":"6"},{"position":"4","car-driven":"Renault","drivers-number":"3","drivers-name":"Giancarlo Fisichella","laps":"77","final-time":"+1 lap","points-earned":"5"},{"position":"5","car-driven":"Sauber BMW","drivers-number":"10","drivers-name":"Robert Kubica","laps":"77","final-time":"+1 lap","points-earned":"4"},{"position":"6","car-driven":"Sauber BMW","drivers-number":"9","drivers-name":"Nick Heidfeld","laps":"77","final-time":"+1 lap","points-earned":"3"},{"position":"7","car-driven":"Williams Toyota","drivers-number":"17","drivers-name":"Alexander Wurz","laps":"77","final-time":"+1 lap","points-earned":"2"},{"position":"8","car-driven":"Ferrari","drivers-number":"6","drivers-name":"Kimi Räikkönen","laps":"77","final-time":"+1 lap","points-earned":"1"},{"position":"9","car-driven":"STR Ferrari","drivers-number":"19","drivers-name":"Scott Speed","laps":"77","final-time":"+1 lap","points-earned":"0"},{"position":"10","car-driven":"Honda","drivers-number":"8","drivers-name":"Rubens Barrichello","laps":"77","final-time":"+1 lap","points-earned":"0"},{"position":"11","car-driven":"Honda","drivers-number":"7","drivers-name":"Jenson Button","laps":"77","final-time":"+1 lap","points-earned":"0"},{"position":"12","car-driven":"Williams Toyota","drivers-number":"16","drivers-name":"Nico Rosberg","laps":"77","final-time":"+1 lap","points-earned":"0"},{"position":"13","car-driven":"Renault","drivers-number":"4","drivers-name":"Heikki Kovalainen","laps":"76","final-time":"DNF","points-earned":"0"},{"position":"14","car-driven":"Red Bull Renault","drivers-number":"14","drivers-name":"David Coulthard","laps":"76","final-time":"+2 laps","points-earned":"0"},{"position":"15","car-driven":"Toyota","drivers-number":"12","drivers-name":"Jarno Trulli","laps":"76","final-time":"+2 laps","points-earned":"0"},{"position":"16","car-driven":"Toyota","drivers-number":"11","drivers-name":"Ralf Schumacher","laps":"76","final-time":"+2 laps","points-earned":"0"},{"position":"17","car-driven":"Super Aguri Honda","drivers-number":"22","drivers-name":"Takuma Sato","laps":"76","final-time":"+2 laps","points-earned":"0"},{"position":"18","car-driven":"Super Aguri Honda","drivers-number":"23","drivers-name":"Anthony Davidson","laps":"76","final-time":"+2 laps","points-earned":"0"},{"position":"19","car-driven":"Spyker Ferrari","drivers-number":"21","drivers-name":"Christijan Albers","laps":"70","final-time":"DNF","points-earned":"0"},{"position":"NC","car-driven":"Spyker Ferrari","drivers-number":"20","drivers-name":"Adrian Sutil","laps":"53","final-time":"DNF","points-earned":"0"},{"position":"NC","car-driven":"Red Bull Renault","drivers-number":"15","drivers-name":"Mark Webber","laps":"17","final-time":"DNF","points-earned":"0"},{"position":"NC","car-driven":"STR Ferrari","drivers-number":"18","drivers-name":"Vitantonio Liuzzi","laps":"1","final-time":"DNF","points-earned":"0"}]},{"race-name":"Canada","winner":"Lewis Hamilton","winner-car":"McLaren Mercedes","date":"10/6/2007","laps":70,"final-grid":[{"position":"1","car-driven":"McLaren Mercedes","drivers-number":"2","drivers-name":"Lewis Hamilton","laps":"70","final-time":"1:44:11.292","points-earned":"10","race":"Canada"},{"position":"2","car-driven":"Sauber BMW","drivers-number":"9","drivers-name":"Nick Heidfeld","laps":"70","final-time":"+4.343s","points-earned":"8"},{"position":"3","car-driven":"Williams Toyota","drivers-number":"17","drivers-name":"Alexander Wurz","laps":"70","final-time":"+5.325s","points-earned":"6"},{"position":"4","car-driven":"Renault","drivers-number":"4","drivers-name":"Heikki Kovalainen","laps":"70","final-time":"+6.729s","points-earned":"5"},{"position":"5","car-driven":"Ferrari","drivers-number":"6","drivers-name":"Kimi Räikkönen","laps":"70","final-time":"+13.007s","points-earned":"4"},{"position":"6","car-driven":"Super Aguri Honda","drivers-number":"22","drivers-name":"Takuma Sato","laps":"70","final-time":"+16.698s","points-earned":"3"},{"position":"7","car-driven":"McLaren Mercedes","drivers-number":"1","drivers-name":"Fernando Alonso","laps":"70","final-time":"+21.936s","points-earned":"2"},{"position":"8","car-driven":"Toyota","drivers-number":"11","drivers-name":"Ralf Schumacher","laps":"70","final-time":"+22.888s","points-earned":"1"},{"position":"9","car-driven":"Red Bull Renault","drivers-number":"15","drivers-name":"Mark Webber","laps":"70","final-time":"+22.960s","points-earned":"0"},{"position":"10","car-driven":"Williams Toyota","drivers-number":"16","drivers-name":"Nico Rosberg","laps":"70","final-time":"+23.984s","points-earned":"0"},{"position":"11","car-driven":"Super Aguri Honda","drivers-number":"23","drivers-name":"Anthony Davidson","laps":"70","final-time":"+24.318s","points-earned":"0"},{"position":"12","car-driven":"Honda","drivers-number":"8","drivers-name":"Rubens Barrichello","laps":"70","final-time":"+30.439s","points-earned":"0"},{"position":"NC","car-driven":"Toyota","drivers-number":"12","drivers-name":"Jarno Trulli","laps":"58","final-time":"DNF","points-earned":"0"},{"position":"NC","car-driven":"STR Ferrari","drivers-number":"18","drivers-name":"Vitantonio Liuzzi","laps":"54","final-time":"DNF","points-earned":"0"},{"position":"NC","car-driven":"Spyker Ferrari","drivers-number":"21","drivers-name":"Christijan Albers","laps":"47","final-time":"DNF","points-earned":"0"},{"position":"NC","car-driven":"Red Bull Renault","drivers-number":"14","drivers-name":"David Coulthard","laps":"36","final-time":"DNF","points-earned":"0"},{"position":"NC","car-driven":"Sauber BMW","drivers-number":"10","drivers-name":"Robert Kubica","laps":"26","final-time":"DNF","points-earned":"0"},{"position":"NC","car-driven":"Spyker Ferrari","drivers-number":"20","drivers-name":"Adrian Sutil","laps":"21","final-time":"DNF","points-earned":"0"},{"position":"NC","car-driven":"STR Ferrari","drivers-number":"19","drivers-name":"Scott Speed","laps":"8","final-time":"DNF","points-earned":"0"},{"position":"NC","car-driven":"Honda","drivers-number":"7","drivers-name":"Jenson Button","laps":"0","final-time":"DNF","points-earned":"0"}]},{"race-name":"United States","winner":"Lewis Hamilton","winner-car":"McLaren Mercedes","date":"17/6/2007","laps":73,"final-grid":[{"position":"1","car-driven":"McLaren Mercedes","drivers-number":"2","drivers-name":"Lewis Hamilton","laps":"73","final-time":"1:31:09.965","points-earned":"10","race":"United States"},{"position":"2","car-driven":"McLaren Mercedes","drivers-number":"1","drivers-name":"Fernando Alonso","laps":"73","final-time":"+1.518s","points-earned":"8"},{"position":"3","car-driven":"Ferrari","drivers-number":"5","drivers-name":"Felipe Massa","laps":"73","final-time":"+12.842s","points-earned":"6"},{"position":"4","car-driven":"Ferrari","drivers-number":"6","drivers-name":"Kimi Räikkönen","laps":"73","final-time":"+15.422s","points-earned":"5"},{"position":"5","car-driven":"Renault","drivers-number":"4","drivers-name":"Heikki Kovalainen","laps":"73","final-time":"+41.402s","points-earned":"4"},{"position":"6","car-driven":"Toyota","drivers-number":"12","drivers-name":"Jarno Trulli","laps":"73","final-time":"+66.703s","points-earned":"3"},{"position":"7","car-driven":"Red Bull Renault","drivers-number":"15","drivers-name":"Mark Webber","laps":"73","final-time":"+67.331s","points-earned":"2"},{"position":"8","car-driven":"Sauber BMW","drivers-number":"10","drivers-name":"Sebastian Vettel","laps":"73","final-time":"+67.783s","points-earned":"1"},{"position":"9","car-driven":"Renault","drivers-number":"3","drivers-name":"Giancarlo Fisichella","laps":"72","final-time":"+1 lap","points-earned":"0"},{"position":"10","car-driven":"Williams Toyota","drivers-number":"17","drivers-name":"Alexander Wurz","laps":"72","final-time":"+1 lap","points-earned":"0"},{"position":"11","car-driven":"Super Aguri Honda","drivers-number":"23","drivers-name":"Anthony Davidson","laps":"72","final-time":"+1 lap","points-earned":"0"},{"position":"12","car-driven":"Honda","drivers-number":"7","drivers-name":"Jenson Button","laps":"72","final-time":"+1 lap","points-earned":"0"},{"position":"13","car-driven":"STR Ferrari","drivers-number":"19","drivers-name":"Scott Speed","laps":"71","final-time":"+2 laps","points-earned":"0"},{"position":"14","car-driven":"Spyker Ferrari","drivers-number":"20","drivers-name":"Adrian Sutil","laps":"71","final-time":"+2 laps","points-earned":"0"},{"position":"15","car-driven":"Spyker Ferrari","drivers-number":"21","drivers-name":"Christijan Albers","laps":"70","final-time":"+3 laps","points-earned":"0"},{"position":"16","car-driven":"Williams Toyota","drivers-number":"16","drivers-name":"Nico Rosberg","laps":"68","final-time":"DNF","points-earned":"0"},{"position":"17","car-driven":"STR Ferrari","drivers-number":"18","drivers-name":"Vitantonio Liuzzi","laps":"68","final-time":"DNF","points-earned":"0"},{"position":"NC","car-driven":"Sauber BMW","drivers-number":"9","drivers-name":"Nick Heidfeld","laps":"55","final-time":"DNF","points-earned":"0"},{"position":"NC","car-driven":"Super Aguri Honda","drivers-number":"22","drivers-name":"Takuma Sato","laps":"13","final-time":"DNF","points-earned":"0"},{"position":"NC","car-driven":"Red Bull Renault","drivers-number":"14","drivers-name":"David Coulthard","laps":"0","final-time":"DNF","points-earned":"0"},{"position":"NC","car-driven":"Toyota","drivers-number":"11","drivers-name":"Ralf Schumacher","laps":"0","final-time":"DNF","points-earned":"0"},{"position":"NC","car-driven":"Honda","drivers-number":"8","drivers-name":"Rubens Barrichello","laps":"0","final-time":"DNF","points-earned":"0"}]},{"race-name":"France","winner":"Kimi Räikkönen","winner-car":"Ferrari","date":"1/7/2007","laps":70,"final-grid":[{"position":"1","car-driven":"Ferrari","drivers-number":"6","drivers-name":"Kimi Räikkönen","laps":"70","final-time":"1:30:54.200","points-earned":"10","race":"France"},{"position":"2","car-driven":"Ferrari","drivers-number":"5","drivers-name":"Felipe Massa","laps":"70","final-time":"+2.414s","points-earned":"8"},{"position":"3","car-driven":"McLaren Mercedes","drivers-number":"2","drivers-name":"Lewis Hamilton","laps":"70","final-time":"+32.153s","points-earned":"6"},{"position":"4","car-driven":"Sauber BMW","drivers-number":"10","drivers-name":"Robert Kubica","laps":"70","final-time":"+41.727s","points-earned":"5"},{"position":"5","car-driven":"Sauber BMW","drivers-number":"9","drivers-name":"Nick Heidfeld","laps":"70","final-time":"+48.801s","points-earned":"4"},{"position":"6","car-driven":"Renault","drivers-number":"3","drivers-name":"Giancarlo Fisichella","laps":"70","final-time":"+52.210s","points-earned":"3"},{"position":"7","car-driven":"McLaren Mercedes","drivers-number":"1","drivers-name":"Fernando Alonso","laps":"70","final-time":"+56.516s","points-earned":"2"},{"position":"8","car-driven":"Honda","drivers-number":"7","drivers-name":"Jenson Button","laps":"70","final-time":"+58.885s","points-earned":"1"},{"position":"9","car-driven":"Williams Toyota","drivers-number":"16","drivers-name":"Nico Rosberg","laps":"70","final-time":"+68.505s","points-earned":"0"},{"position":"10","car-driven":"Toyota","drivers-number":"11","drivers-name":"Ralf Schumacher","laps":"69","final-time":"+1 lap","points-earned":"0"},{"position":"11","car-driven":"Honda","drivers-number":"8","drivers-name":"Rubens Barrichello","laps":"69","final-time":"+1 lap","points-earned":"0"},{"position":"12","car-driven":"Red Bull Renault","drivers-number":"15","drivers-name":"Mark Webber","laps":"69","final-time":"+1 lap","points-earned":"0"},{"position":"13","car-driven":"Red Bull Renault","drivers-number":"14","drivers-name":"David Coulthard","laps":"69","final-time":"+1 lap","points-earned":"0"},{"position":"14","car-driven":"Williams Toyota","drivers-number":"17","drivers-name":"Alexander Wurz","laps":"69","final-time":"+1 lap","points-earned":"0"},{"position":"15","car-driven":"Renault","drivers-number":"4","drivers-name":"Heikki Kovalainen","laps":"69","final-time":"+1 lap","points-earned":"0"},{"position":"16","car-driven":"Super Aguri Honda","drivers-number":"22","drivers-name":"Takuma Sato","laps":"68","final-time":"+2 laps","points-earned":"0"},{"position":"17","car-driven":"Spyker Ferrari","drivers-number":"20","drivers-name":"Adrian Sutil","laps":"68","final-time":"+2 laps","points-earned":"0"},{"position":"NC","car-driven":"STR Ferrari","drivers-number":"19","drivers-name":"Scott Speed","laps":"55","final-time":"DNF","points-earned":"0"},{"position":"NC","car-driven":"Spyker Ferrari","drivers-number":"21","drivers-name":"Christijan Albers","laps":"28","final-time":"DNF","points-earned":"0"},{"position":"NC","car-driven":"Super Aguri Honda","drivers-number":"23","drivers-name":"Anthony Davidson","laps":"1","final-time":"DNF","points-earned":"0"},{"position":"NC","car-driven":"Toyota","drivers-number":"12","drivers-name":"Jarno Trulli","laps":"1","final-time":"DNF","points-earned":"0"},{"position":"NC","car-driven":"STR Ferrari","drivers-number":"18","drivers-name":"Vitantonio Liuzzi","laps":"0","final-time":"DNF","points-earned":"0"}]},{"race-name":"Great Britain","winner":"Kimi Räikkönen","winner-car":"Ferrari","date":"8/7/2007","laps":59,"final-grid":[{"position":"1","car-driven":"Ferrari","drivers-number":"6","drivers-name":"Kimi Räikkönen","laps":"59","final-time":"1:21:43.074","points-earned":"10","race":"Great Britain"},{"position":"2","car-driven":"McLaren Mercedes","drivers-number":"1","drivers-name":"Fernando Alonso","laps":"59","final-time":"+2.459s","points-earned":"8"},{"position":"3","car-driven":"McLaren Mercedes","drivers-number":"2","drivers-name":"Lewis Hamilton","laps":"59","final-time":"+39.373s","points-earned":"6"},{"position":"4","car-driven":"Sauber BMW","drivers-number":"10","drivers-name":"Robert Kubica","laps":"59","final-time":"+53.319s","points-earned":"5"},{"position":"5","car-driven":"Ferrari","drivers-number":"5","drivers-name":"Felipe Massa","laps":"59","final-time":"+54.063s","points-earned":"4"},{"position":"6","car-driven":"Sauber BMW","drivers-number":"9","drivers-name":"Nick Heidfeld","laps":"59","final-time":"+56.336s","points-earned":"3"},{"position":"7","car-driven":"Renault","drivers-number":"4","drivers-name":"Heikki Kovalainen","laps":"58","final-time":"+1 lap","points-earned":"2"},{"position":"8","car-driven":"Renault","drivers-number":"3","drivers-name":"Giancarlo Fisichella","laps":"58","final-time":"+1 lap","points-earned":"1"},{"position":"9","car-driven":"Honda","drivers-number":"8","drivers-name":"Rubens Barrichello","laps":"58","final-time":"+1 lap","points-earned":"0"},{"position":"10","car-driven":"Honda","drivers-number":"7","drivers-name":"Jenson Button","laps":"58","final-time":"+1 lap","points-earned":"0"},{"position":"11","car-driven":"Red Bull Renault","drivers-number":"14","drivers-name":"David Coulthard","laps":"58","final-time":"+1 lap","points-earned":"0"},{"position":"12","car-driven":"Williams Toyota","drivers-number":"16","drivers-name":"Nico Rosberg","laps":"58","final-time":"+1 lap","points-earned":"0"},{"position":"13","car-driven":"Williams Toyota","drivers-number":"17","drivers-name":"Alexander Wurz","laps":"58","final-time":"+1 lap","points-earned":"0"},{"position":"14","car-driven":"Super Aguri Honda","drivers-number":"22","drivers-name":"Takuma Sato","laps":"57","final-time":"+2 laps","points-earned":"0"},{"position":"15","car-driven":"Spyker Ferrari","drivers-number":"21","drivers-name":"Christijan Albers","laps":"57","final-time":"+2 laps","points-earned":"0"},{"position":"16","car-driven":"STR Ferrari","drivers-number":"18","drivers-name":"Vitantonio Liuzzi","laps":"53","final-time":"DNF","points-earned":"0"},{"position":"NC","car-driven":"Toyota","drivers-number":"12","drivers-name":"Jarno Trulli","laps":"43","final-time":"DNF","points-earned":"0"},{"position":"NC","car-driven":"Super Aguri Honda","drivers-number":"23","drivers-name":"Anthony Davidson","laps":"35","final-time":"DNF","points-earned":"0"},{"position":"NC","car-driven":"STR Ferrari","drivers-number":"19","drivers-name":"Scott Speed","laps":"29","final-time":"DNF","points-earned":"0"},{"position":"NC","car-driven":"Toyota","drivers-number":"11","drivers-name":"Ralf Schumacher","laps":"22","final-time":"DNF","points-earned":"0"},{"position":"NC","car-driven":"Spyker Ferrari","drivers-number":"20","drivers-name":"Adrian Sutil","laps":"16","final-time":"DNF","points-earned":"0"},{"position":"NC","car-driven":"Red Bull Renault","drivers-number":"15","drivers-name":"Mark Webber","laps":"8","final-time":"DNF","points-earned":"0"}]},{"race-name":"Europe","winner":"Fernando Alonso","winner-car":"McLaren Mercedes","date":"22/7/2007","laps":60,"final-grid":[{"position":"1","car-driven":"McLaren Mercedes","drivers-number":"1","drivers-name":"Fernando Alonso","laps":"60","final-time":"2:06:26.358","points-earned":"10","race":"Germany"},{"position":"2","car-driven":"Ferrari","drivers-number":"5","drivers-name":"Felipe Massa","laps":"60","final-time":"+8.155s","points-earned":"8"},{"position":"3","car-driven":"Red Bull Renault","drivers-number":"15","drivers-name":"Mark Webber","laps":"60","final-time":"+65.674s","points-earned":"6"},{"position":"4","car-driven":"Williams Toyota","drivers-number":"17","drivers-name":"Alexander Wurz","laps":"60","final-time":"+65.937s","points-earned":"5"},{"position":"5","car-driven":"Red Bull Renault","drivers-number":"14","drivers-name":"David Coulthard","laps":"60","final-time":"+73.656s","points-earned":"4"},{"position":"6","car-driven":"Sauber BMW","drivers-number":"9","drivers-name":"Nick Heidfeld","laps":"60","final-time":"+80.298s","points-earned":"3"},{"position":"7","car-driven":"Sauber BMW","drivers-number":"10","drivers-name":"Robert Kubica","laps":"60","final-time":"+82.415s","points-earned":"2"},{"position":"8","car-driven":"Renault","drivers-number":"4","drivers-name":"Heikki Kovalainen","laps":"59","final-time":"+1 lap","points-earned":"1"},{"position":"9","car-driven":"McLaren Mercedes","drivers-number":"2","drivers-name":"Lewis Hamilton","laps":"59","final-time":"+1 lap","points-earned":"0"},{"position":"10","car-driven":"Renault","drivers-number":"3","drivers-name":"Giancarlo Fisichella","laps":"59","final-time":"+1 lap","points-earned":"0"},{"position":"11","car-driven":"Honda","drivers-number":"8","drivers-name":"Rubens Barrichello","laps":"59","final-time":"+1 lap","points-earned":"0"},{"position":"12","car-driven":"Super Aguri Honda","drivers-number":"23","drivers-name":"Anthony Davidson","laps":"59","final-time":"+1 lap","points-earned":"0"},{"position":"13","car-driven":"Toyota","drivers-number":"12","drivers-name":"Jarno Trulli","laps":"59","final-time":"+1 lap","points-earned":"0"},{"position":"NC","car-driven":"Ferrari","drivers-number":"6","drivers-name":"Kimi Räikkönen","laps":"34","final-time":"DNF","points-earned":"0"},{"position":"NC","car-driven":"Super Aguri Honda","drivers-number":"22","drivers-name":"Takuma Sato","laps":"19","final-time":"DNF","points-earned":"0"},{"position":"NC","car-driven":"Toyota","drivers-number":"11","drivers-name":"Ralf Schumacher","laps":"18","final-time":"DNF","points-earned":"0"},{"position":"NC","car-driven":"Spyker Ferrari","drivers-number":"21","drivers-name":"Markus Winkelhock","laps":"13","final-time":"DNF","points-earned":"0"},{"position":"NC","car-driven":"Honda","drivers-number":"7","drivers-name":"Jenson Button","laps":"2","final-time":"DNF","points-earned":"0"},{"position":"NC","car-driven":"Spyker Ferrari","drivers-number":"20","drivers-name":"Adrian Sutil","laps":"2","final-time":"DNF","points-earned":"0"},{"position":"NC","car-driven":"Williams Toyota","drivers-number":"16","drivers-name":"Nico Rosberg","laps":"2","final-time":"DNF","points-earned":"0"},{"position":"NC","car-driven":"STR Ferrari","drivers-number":"19","drivers-name":"Scott Speed","laps":"2","final-time":"DNF","points-earned":"0"},{"position":"NC","car-driven":"STR Ferrari","drivers-number":"18","drivers-name":"Vitantonio Liuzzi","laps":"2","final-time":"DNF","points-earned":"0"}]},{"race-name":"Hungary","winner":"Lewis Hamilton","winner-car":"McLaren Mercedes","date":"5/8/2007","laps":70,"final-grid":[{"position":"1","car-driven":"McLaren Mercedes","drivers-number":"2","drivers-name":"Lewis Hamilton","laps":"70","final-time":"1:35:52.991","points-earned":"10","race":"Hungary"},{"position":"2","car-driven":"Ferrari","drivers-number":"6","drivers-name":"Kimi Räikkönen","laps":"70","final-time":"+0.715s","points-earned":"8"},{"position":"3","car-driven":"Sauber BMW","drivers-number":"9","drivers-name":"Nick Heidfeld","laps":"70","final-time":"+43.129s","points-earned":"6"},{"position":"4","car-driven":"McLaren Mercedes","drivers-number":"1","drivers-name":"Fernando Alonso","laps":"70","final-time":"+44.858s","points-earned":"5"},{"position":"5","car-driven":"Sauber BMW","drivers-number":"10","drivers-name":"Robert Kubica","laps":"70","final-time":"+47.616s","points-earned":"4"},{"position":"6","car-driven":"Toyota","drivers-number":"11","drivers-name":"Ralf Schumacher","laps":"70","final-time":"+50.669s","points-earned":"3"},{"position":"7","car-driven":"Williams Toyota","drivers-number":"16","drivers-name":"Nico Rosberg","laps":"70","final-time":"+59.139s","points-earned":"2"},{"position":"8","car-driven":"Renault","drivers-number":"4","drivers-name":"Heikki Kovalainen","laps":"70","final-time":"+68.104s","points-earned":"1"},{"position":"9","car-driven":"Red Bull Renault","drivers-number":"15","drivers-name":"Mark Webber","laps":"70","final-time":"+76.331s","points-earned":"0"},{"position":"10","car-driven":"Toyota","drivers-number":"12","drivers-name":"Jarno Trulli","laps":"69","final-time":"+1 lap","points-earned":"0"},{"position":"11","car-driven":"Red Bull Renault","drivers-number":"14","drivers-name":"David Coulthard","laps":"69","final-time":"+1 lap","points-earned":"0"},{"position":"12","car-driven":"Renault","drivers-number":"3","drivers-name":"Giancarlo Fisichella","laps":"69","final-time":"+1 lap","points-earned":"0"},{"position":"13","car-driven":"Ferrari","drivers-number":"5","drivers-name":"Felipe Massa","laps":"69","final-time":"+1 lap","points-earned":"0"},{"position":"14","car-driven":"Williams Toyota","drivers-number":"17","drivers-name":"Alexander Wurz","laps":"69","final-time":"+1 lap","points-earned":"0"},{"position":"15","car-driven":"Super Aguri Honda","drivers-number":"22","drivers-name":"Takuma Sato","laps":"69","final-time":"+1 lap","points-earned":"0"},{"position":"16","car-driven":"STR Ferrari","drivers-number":"19","drivers-name":"Sebastian Vettel","laps":"69","final-time":"+1 lap","points-earned":"0"},{"position":"17","car-driven":"Spyker Ferrari","drivers-number":"20","drivers-name":"Adrian Sutil","laps":"68","final-time":"+2 laps","points-earned":"0"},{"position":"18","car-driven":"Honda","drivers-number":"8","drivers-name":"Rubens Barrichello","laps":"68","final-time":"+2 laps","points-earned":"0"},{"position":"NC","car-driven":"STR Ferrari","drivers-number":"18","drivers-name":"Vitantonio Liuzzi","laps":"42","final-time":"DNF","points-earned":"0"},{"position":"NC","car-driven":"Super Aguri Honda","drivers-number":"23","drivers-name":"Anthony Davidson","laps":"41","final-time":"DNF","points-earned":"0"},{"position":"NC","car-driven":"Honda","drivers-number":"7","drivers-name":"Jenson Button","laps":"35","final-time":"DNF","points-earned":"0"},{"position":"NC","car-driven":"Spyker Ferrari","drivers-number":"21","drivers-name":"Sakon Yamamoto","laps":"4","final-time":"DNF","points-earned":"0"}]},{"race-name":"Turkey","winner":"Felipe Massa","winner-car":"Ferrari","date":"26/8/2007","laps":58,"final-grid":[{"position":"1","car-driven":"Ferrari","drivers-number":"5","drivers-name":"Felipe Massa","laps":"58","final-time":"1:26:42.161","points-earned":"10","race":"Turkey"},{"position":"2","car-driven":"Ferrari","drivers-number":"6","drivers-name":"Kimi Räikkönen","laps":"58","final-time":"+2.275s","points-earned":"8"},{"position":"3","car-driven":"McLaren Mercedes","drivers-number":"1","drivers-name":"Fernando Alonso","laps":"58","final-time":"+26.181s","points-earned":"6"},{"position":"4","car-driven":"Sauber BMW","drivers-number":"9","drivers-name":"Nick Heidfeld","laps":"58","final-time":"+39.674s","points-earned":"5"},{"position":"5","car-driven":"McLaren Mercedes","drivers-number":"2","drivers-name":"Lewis Hamilton","laps":"58","final-time":"+45.085s","points-earned":"4"},{"position":"6","car-driven":"Renault","drivers-number":"4","drivers-name":"Heikki Kovalainen","laps":"58","final-time":"+46.169s","points-earned":"3"},{"position":"7","car-driven":"Williams Toyota","drivers-number":"16","drivers-name":"Nico Rosberg","laps":"58","final-time":"+55.778s","points-earned":"2"},{"position":"8","car-driven":"Sauber BMW","drivers-number":"10","drivers-name":"Robert Kubica","laps":"58","final-time":"+56.707s","points-earned":"1"},{"position":"9","car-driven":"Renault","drivers-number":"3","drivers-name":"Giancarlo Fisichella","laps":"58","final-time":"+59.491s","points-earned":"0"},{"position":"10","car-driven":"Red Bull Renault","drivers-number":"14","drivers-name":"David Coulthard","laps":"58","final-time":"+71.009s","points-earned":"0"},{"position":"11","car-driven":"Williams Toyota","drivers-number":"17","drivers-name":"Alexander Wurz","laps":"58","final-time":"+79.628s","points-earned":"0"},{"position":"12","car-driven":"Toyota","drivers-number":"11","drivers-name":"Ralf Schumacher","laps":"57","final-time":"+1 lap","points-earned":"0"},{"position":"13","car-driven":"Honda","drivers-number":"7","drivers-name":"Jenson Button","laps":"57","final-time":"+1 lap","points-earned":"0"},{"position":"14","car-driven":"Super Aguri Honda","drivers-number":"23","drivers-name":"Anthony Davidson","laps":"57","final-time":"+1 lap","points-earned":"0"},{"position":"15","car-driven":"STR Ferrari","drivers-number":"18","drivers-name":"Vitantonio Liuzzi","laps":"57","final-time":"+1 lap","points-earned":"0"},{"position":"16","car-driven":"Toyota","drivers-number":"12","drivers-name":"Jarno Trulli","laps":"57","final-time":"+1 lap","points-earned":"0"},{"position":"17","car-driven":"Honda","drivers-number":"8","drivers-name":"Rubens Barrichello","laps":"57","final-time":"+1 lap","points-earned":"0"},{"position":"18","car-driven":"Super Aguri Honda","drivers-number":"22","drivers-name":"Takuma Sato","laps":"57","final-time":"+1 lap","points-earned":"0"},{"position":"19","car-driven":"STR Ferrari","drivers-number":"19","drivers-name":"Sebastian Vettel","laps":"57","final-time":"+1 lap","points-earned":"0"},{"position":"20","car-driven":"Spyker Ferrari","drivers-number":"21","drivers-name":"Sakon Yamamoto","laps":"56","final-time":"+2 laps","points-earned":"0"},{"position":"21","car-driven":"Spyker Ferrari","drivers-number":"20","drivers-name":"Adrian Sutil","laps":"53","final-time":"DNF","points-earned":"0"},{"position":"NC","car-driven":"Red Bull Renault","drivers-number":"15","drivers-name":"Mark Webber","laps":"9","final-time":"DNF","points-earned":"0"}]},{"race-name":"Italy","winner":"Fernando Alonso","winner-car":"McLaren Mercedes","date":"9/9/2007","laps":53,"final-grid":[{"position":"1","car-driven":"McLaren Mercedes","drivers-number":"1","drivers-name":"Fernando Alonso","laps":"53","final-time":"1:18:37.806","points-earned":"10","race":"Italy"},{"position":"2","car-driven":"McLaren Mercedes","drivers-number":"2","drivers-name":"Lewis Hamilton","laps":"53","final-time":"+6.062s","points-earned":"8"},{"position":"3","car-driven":"Ferrari","drivers-number":"6","drivers-name":"Kimi Räikkönen","laps":"53","final-time":"+27.325s","points-earned":"6"},{"position":"4","car-driven":"Sauber BMW","drivers-number":"9","drivers-name":"Nick Heidfeld","laps":"53","final-time":"+56.562s","points-earned":"5"},{"position":"5","car-driven":"Sauber BMW","drivers-number":"10","drivers-name":"Robert Kubica","laps":"53","final-time":"+60.558s","points-earned":"4"},{"position":"6","car-driven":"Williams Toyota","drivers-number":"16","drivers-name":"Nico Rosberg","laps":"53","final-time":"+65.810s","points-earned":"3"},{"position":"7","car-driven":"Renault","drivers-number":"4","drivers-name":"Heikki Kovalainen","laps":"53","final-time":"+66.751s","points-earned":"2"},{"position":"8","car-driven":"Honda","drivers-number":"7","drivers-name":"Jenson Button","laps":"53","final-time":"+72.168s","points-earned":"1"},{"position":"9","car-driven":"Red Bull Renault","drivers-number":"15","drivers-name":"Mark Webber","laps":"53","final-time":"+75.879s","points-earned":"0"},{"position":"10","car-driven":"Honda","drivers-number":"8","drivers-name":"Rubens Barrichello","laps":"53","final-time":"+76.958s","points-earned":"0"},{"position":"11","car-driven":"Toyota","drivers-number":"12","drivers-name":"Jarno Trulli","laps":"53","final-time":"+77.736s","points-earned":"0"},{"position":"12","car-driven":"Renault","drivers-number":"3","drivers-name":"Giancarlo Fisichella","laps":"52","final-time":"+1 lap","points-earned":"0"},{"position":"13","car-driven":"Williams Toyota","drivers-number":"17","drivers-name":"Alexander Wurz","laps":"52","final-time":"+1 lap","points-earned":"0"},{"position":"14","car-driven":"Super Aguri Honda","drivers-number":"23","drivers-name":"Anthony Davidson","laps":"52","final-time":"+1 lap","points-earned":"0"},{"position":"15","car-driven":"Toyota","drivers-number":"11","drivers-name":"Ralf Schumacher","laps":"52","final-time":"+1 lap","points-earned":"0"},{"position":"16","car-driven":"Super Aguri Honda","drivers-number":"22","drivers-name":"Takuma Sato","laps":"52","final-time":"+1 lap","points-earned":"0"},{"position":"17","car-driven":"STR Ferrari","drivers-number":"18","drivers-name":"Vitantonio Liuzzi","laps":"52","final-time":"+1 lap","points-earned":"0"},{"position":"18","car-driven":"STR Ferrari","drivers-number":"19","drivers-name":"Sebastian Vettel","laps":"52","final-time":"+1 lap","points-earned":"0"},{"position":"19","car-driven":"Spyker Ferrari","drivers-number":"20","drivers-name":"Adrian Sutil","laps":"52","final-time":"+1 lap","points-earned":"0"},{"position":"20","car-driven":"Spyker Ferrari","drivers-number":"21","drivers-name":"Sakon Yamamoto","laps":"52","final-time":"+1 lap","points-earned":"0"},{"position":"NC","car-driven":"Ferrari","drivers-number":"5","drivers-name":"Felipe Massa","laps":"10","final-time":"DNF","points-earned":"0"},{"position":"NC","car-driven":"Red Bull Renault","drivers-number":"14","drivers-name":"David Coulthard","laps":"1","final-time":"DNF","points-earned":"0"}]},{"race-name":"Belgium","winner":"Kimi Räikkönen","winner-car":"Ferrari","date":"16/9/2007","laps":44,"final-grid":[{"position":"1","car-driven":"Ferrari","drivers-number":"6","drivers-name":"Kimi Räikkönen","laps":"44","final-time":"1:20:39.066","points-earned":"10","race":"Belgium"},{"position":"2","car-driven":"Ferrari","drivers-number":"5","drivers-name":"Felipe Massa","laps":"44","final-time":"+4.695s","points-earned":"8"},{"position":"3","car-driven":"McLaren Mercedes","drivers-number":"1","drivers-name":"Fernando Alonso","laps":"44","final-time":"+14.343s","points-earned":"6"},{"position":"4","car-driven":"McLaren Mercedes","drivers-number":"2","drivers-name":"Lewis Hamilton","laps":"44","final-time":"+23.615s","points-earned":"5"},{"position":"5","car-driven":"Sauber BMW","drivers-number":"9","drivers-name":"Nick Heidfeld","laps":"44","final-time":"+51.879s","points-earned":"4"},{"position":"6","car-driven":"Williams Toyota","drivers-number":"16","drivers-name":"Nico Rosberg","laps":"44","final-time":"+76.876s","points-earned":"3"},{"position":"7","car-driven":"Red Bull Renault","drivers-number":"15","drivers-name":"Mark Webber","laps":"44","final-time":"+80.639s","points-earned":"2"},{"position":"8","car-driven":"Renault","drivers-number":"4","drivers-name":"Heikki Kovalainen","laps":"44","final-time":"+85.106s","points-earned":"1"},{"position":"9","car-driven":"Sauber BMW","drivers-number":"10","drivers-name":"Robert Kubica","laps":"44","final-time":"+85.661s","points-earned":"0"},{"position":"10","car-driven":"Toyota","drivers-number":"11","drivers-name":"Ralf Schumacher","laps":"44","final-time":"+88.574s","points-earned":"0"},{"position":"11","car-driven":"Toyota","drivers-number":"12","drivers-name":"Jarno Trulli","laps":"44","final-time":"+103.653s","points-earned":"0"},{"position":"12","car-driven":"STR Ferrari","drivers-number":"18","drivers-name":"Vitantonio Liuzzi","laps":"43","final-time":"+1 lap","points-earned":"0"},{"position":"13","car-driven":"Honda","drivers-number":"8","drivers-name":"Rubens Barrichello","laps":"43","final-time":"+1 lap","points-earned":"0"},{"position":"14","car-driven":"Spyker Ferrari","drivers-number":"20","drivers-name":"Adrian Sutil","laps":"43","final-time":"+1 lap","points-earned":"0"},{"position":"15","car-driven":"Super Aguri Honda","drivers-number":"22","drivers-name":"Takuma Sato","laps":"43","final-time":"+1 lap","points-earned":"0"},{"position":"16","car-driven":"Super Aguri Honda","drivers-number":"23","drivers-name":"Anthony Davidson","laps":"43","final-time":"+1 lap","points-earned":"0"},{"position":"17","car-driven":"Spyker Ferrari","drivers-number":"21","drivers-name":"Sakon Yamamoto","laps":"43","final-time":"+1 lap","points-earned":"0"},{"position":"NC","car-driven":"Honda","drivers-number":"7","drivers-name":"Jenson Button","laps":"36","final-time":"DNF","points-earned":"0"},{"position":"NC","car-driven":"Williams Toyota","drivers-number":"17","drivers-name":"Alexander Wurz","laps":"34","final-time":"DNF","points-earned":"0"},{"position":"NC","car-driven":"Red Bull Renault","drivers-number":"14","drivers-name":"David Coulthard","laps":"29","final-time":"DNF","points-earned":"0"},{"position":"NC","car-driven":"STR Ferrari","drivers-number":"19","drivers-name":"Sebastian Vettel","laps":"8","final-time":"DNF","points-earned":"0"},{"position":"NC","car-driven":"Renault","drivers-number":"3","drivers-name":"Giancarlo Fisichella","laps":"1","final-time":"DNF","points-earned":"0"}]},{"race-name":"Japan","winner":"Lewis Hamilton","winner-car":"McLaren Mercedes","date":"30/9/2007","laps":67,"final-grid":[{"position":"1","car-driven":"McLaren Mercedes","drivers-number":"2","drivers-name":"Lewis Hamilton","laps":"67","final-time":"2:00:34.579","points-earned":"10","race":"Japan"},{"position":"2","car-driven":"Renault","drivers-number":"4","drivers-name":"Heikki Kovalainen","laps":"67","final-time":"+8.377s","points-earned":"8"},{"position":"3","car-driven":"Ferrari","drivers-number":"6","drivers-name":"Kimi Räikkönen","laps":"67","final-time":"+9.478s","points-earned":"6"},{"position":"4","car-driven":"Red Bull Renault","drivers-number":"14","drivers-name":"David Coulthard","laps":"67","final-time":"+20.297s","points-earned":"5"},{"position":"5","car-driven":"Renault","drivers-number":"3","drivers-name":"Giancarlo Fisichella","laps":"67","final-time":"+38.864s","points-earned":"4"},{"position":"6","car-driven":"Ferrari","drivers-number":"5","drivers-name":"Felipe Massa","laps":"67","final-time":"+49.042s","points-earned":"3"},{"position":"7","car-driven":"Sauber BMW","drivers-number":"10","drivers-name":"Robert Kubica","laps":"67","final-time":"+49.285s","points-earned":"2"},{"position":"8","car-driven":"Spyker Ferrari","drivers-number":"20","drivers-name":"Adrian Sutil","laps":"67","final-time":"+60.129s","points-earned":"1"},{"position":"9","car-driven":"STR Ferrari","drivers-number":"18","drivers-name":"Vitantonio Liuzzi","laps":"67","final-time":"+80.622s","points-earned":"0"},{"position":"10","car-driven":"Honda","drivers-number":"8","drivers-name":"Rubens Barrichello","laps":"67","final-time":"+88.342s","points-earned":"0"},{"position":"11","car-driven":"Honda","drivers-number":"7","drivers-name":"Jenson Button","laps":"66","final-time":"DNF","points-earned":"0"},{"position":"12","car-driven":"Spyker Ferrari","drivers-number":"21","drivers-name":"Sakon Yamamoto","laps":"66","final-time":"+1 lap","points-earned":"0"},{"position":"13","car-driven":"Toyota","drivers-number":"12","drivers-name":"Jarno Trulli","laps":"66","final-time":"+1 lap","points-earned":"0"},{"position":"14","car-driven":"Sauber BMW","drivers-number":"9","drivers-name":"Nick Heidfeld","laps":"65","final-time":"DNF","points-earned":"0"},{"position":"15","car-driven":"Super Aguri Honda","drivers-number":"22","drivers-name":"Takuma Sato","laps":"65","final-time":"DNF","points-earned":"0"},{"position":"NC","car-driven":"Toyota","drivers-number":"11","drivers-name":"Ralf Schumacher","laps":"55","final-time":"DNF","points-earned":"0"},{"position":"NC","car-driven":"Super Aguri Honda","drivers-number":"23","drivers-name":"Anthony Davidson","laps":"54","final-time":"DNF","points-earned":"0"},{"position":"NC","car-driven":"Williams Toyota","drivers-number":"16","drivers-name":"Nico Rosberg","laps":"49","final-time":"DNF","points-earned":"0"},{"position":"NC","car-driven":"STR Ferrari","drivers-number":"19","drivers-name":"Sebastian Vettel","laps":"46","final-time":"DNF","points-earned":"0"},{"position":"NC","car-driven":"Red Bull Renault","drivers-number":"15","drivers-name":"Mark Webber","laps":"45","final-time":"DNF","points-earned":"0"},{"position":"NC","car-driven":"McLaren Mercedes","drivers-number":"1","drivers-name":"Fernando Alonso","laps":"41","final-time":"DNF","points-earned":"0"}]},{"race-name":"China","winner":"Kimi Räikkönen","winner-car":"Ferrari","date":"7/10/2007","laps":56,"final-grid":[{"position":"1","car-driven":"Ferrari","drivers-number":"6","drivers-name":"Kimi Räikkönen","laps":"56","final-time":"1:37:58.395","points-earned":"10","race":"China"},{"position":"2","car-driven":"McLaren Mercedes","drivers-number":"1","drivers-name":"Fernando Alonso","laps":"56","final-time":"+9.806s","points-earned":"8"},{"position":"3","car-driven":"Ferrari","drivers-number":"5","drivers-name":"Felipe Massa","laps":"56","final-time":"+12.891s","points-earned":"6"},{"position":"4","car-driven":"STR Ferrari","drivers-number":"19","drivers-name":"Sebastian Vettel","laps":"56","final-time":"+53.509s","points-earned":"5"},{"position":"5","car-driven":"Honda","drivers-number":"7","drivers-name":"Jenson Button","laps":"56","final-time":"+68.666s","points-earned":"4"},{"position":"6","car-driven":"STR Ferrari","drivers-number":"18","drivers-name":"Vitantonio Liuzzi","laps":"56","final-time":"+73.673s","points-earned":"3"},{"position":"7","car-driven":"Sauber BMW","drivers-number":"9","drivers-name":"Nick Heidfeld","laps":"56","final-time":"+74.224s","points-earned":"2"},{"position":"8","car-driven":"Red Bull Renault","drivers-number":"14","drivers-name":"David Coulthard","laps":"56","final-time":"+80.750s","points-earned":"1"},{"position":"9","car-driven":"Renault","drivers-number":"4","drivers-name":"Heikki Kovalainen","laps":"56","final-time":"+81.186s","points-earned":"0"},{"position":"10","car-driven":"Red Bull Renault","drivers-number":"15","drivers-name":"Mark Webber","laps":"56","final-time":"+84.685s","points-earned":"0"},{"position":"11","car-driven":"Renault","drivers-number":"3","drivers-name":"Giancarlo Fisichella","laps":"56","final-time":"+86.683s","points-earned":"0"},{"position":"12","car-driven":"Williams Toyota","drivers-number":"17","drivers-name":"Alexander Wurz","laps":"55","final-time":"+1 lap","points-earned":"0"},{"position":"13","car-driven":"Toyota","drivers-number":"12","drivers-name":"Jarno Trulli","laps":"55","final-time":"+1 lap","points-earned":"0"},{"position":"14","car-driven":"Super Aguri Honda","drivers-number":"22","drivers-name":"Takuma Sato","laps":"55","final-time":"+1 lap","points-earned":"0"},{"position":"15","car-driven":"Honda","drivers-number":"8","drivers-name":"Rubens Barrichello","laps":"55","final-time":"+1 lap","points-earned":"0"},{"position":"16","car-driven":"Williams Toyota","drivers-number":"16","drivers-name":"Nico Rosberg","laps":"54","final-time":"+2 laps","points-earned":"0"},{"position":"17","car-driven":"Spyker Ferrari","drivers-number":"21","drivers-name":"Sakon Yamamoto","laps":"53","final-time":"+3 laps","points-earned":"0"},{"position":"NC","car-driven":"Sauber BMW","drivers-number":"10","drivers-name":"Robert Kubica","laps":"33","final-time":"DNF","points-earned":"0"},{"position":"NC","car-driven":"McLaren Mercedes","drivers-number":"2","drivers-name":"Lewis Hamilton","laps":"30","final-time":"DNF","points-earned":"0"},{"position":"NC","car-driven":"Toyota","drivers-number":"11","drivers-name":"Ralf Schumacher","laps":"25","final-time":"DNF","points-earned":"0"},{"position":"NC","car-driven":"Spyker Ferrari","drivers-number":"20","drivers-name":"Adrian Sutil","laps":"24","final-time":"DNF","points-earned":"0"},{"position":"NC","car-driven":"Super Aguri Honda","drivers-number":"23","drivers-name":"Anthony Davidson","laps":"11","final-time":"DNF","points-earned":"0"}]},{"race-name":"Brazil","winner":"Kimi Räikkönen","winner-car":"Ferrari","date":"21/10/2007","laps":71,"final-grid":[{"position":"1","car-driven":"Ferrari","drivers-number":"6","drivers-name":"Kimi Räikkönen","laps":"71","final-time":"1:28:15.270","points-earned":"10","race":"Brazil"},{"position":"2","car-driven":"Ferrari","drivers-number":"5","drivers-name":"Felipe Massa","laps":"71","final-time":"+1.493s","points-earned":"8"},{"position":"3","car-driven":"McLaren Mercedes","drivers-number":"1","drivers-name":"Fernando Alonso","laps":"71","final-time":"+57.019s","points-earned":"6"},{"position":"4","car-driven":"Williams Toyota","drivers-number":"16","drivers-name":"Nico Rosberg","laps":"71","final-time":"+62.848s","points-earned":"5"},{"position":"5","car-driven":"Sauber BMW","drivers-number":"10","drivers-name":"Robert Kubica","laps":"71","final-time":"+70.957s","points-earned":"4"},{"position":"6","car-driven":"Sauber BMW","drivers-number":"9","drivers-name":"Nick Heidfeld","laps":"71","final-time":"+71.317s","points-earned":"3"},{"position":"7","car-driven":"McLaren Mercedes","drivers-number":"2","drivers-name":"Lewis Hamilton","laps":"70","final-time":"+1 lap","points-earned":"2"},{"position":"8","car-driven":"Toyota","drivers-number":"12","drivers-name":"Jarno Trulli","laps":"70","final-time":"+1 lap","points-earned":"1"},{"position":"9","car-driven":"Red Bull Renault","drivers-number":"14","drivers-name":"David Coulthard","laps":"70","final-time":"+1 lap","points-earned":"0"},{"position":"10","car-driven":"Williams Toyota","drivers-number":"17","drivers-name":"Kazuki Nakajima","laps":"70","final-time":"+1 lap","points-earned":"0"},{"position":"11","car-driven":"Toyota","drivers-number":"11","drivers-name":"Ralf Schumacher","laps":"70","final-time":"+1 lap","points-earned":"0"},{"position":"12","car-driven":"Super Aguri Honda","drivers-number":"22","drivers-name":"Takuma Sato","laps":"69","final-time":"+2 laps","points-earned":"0"},{"position":"13","car-driven":"STR Ferrari","drivers-number":"18","drivers-name":"Vitantonio Liuzzi","laps":"69","final-time":"+2 laps","points-earned":"0"},{"position":"14","car-driven":"Super Aguri Honda","drivers-number":"23","drivers-name":"Anthony Davidson","laps":"68","final-time":"+3 laps","points-earned":"0"},{"position":"NC","car-driven":"Spyker Ferrari","drivers-number":"20","drivers-name":"Adrian Sutil","laps":"43","final-time":"DNF","points-earned":"0"},{"position":"NC","car-driven":"Honda","drivers-number":"8","drivers-name":"Rubens Barrichello","laps":"40","final-time":"DNF","points-earned":"0"},{"position":"NC","car-driven":"Renault","drivers-number":"4","drivers-name":"Heikki Kovalainen","laps":"35","final-time":"DNF","points-earned":"0"},{"position":"NC","car-driven":"STR Ferrari","drivers-number":"19","drivers-name":"Sebastian Vettel","laps":"34","final-time":"DNF","points-earned":"0"},{"position":"NC","car-driven":"Honda","drivers-number":"7","drivers-name":"Jenson Button","laps":"20","final-time":"DNF","points-earned":"0"},{"position":"NC","car-driven":"Red Bull Renault","drivers-number":"15","drivers-name":"Mark Webber","laps":"14","final-time":"DNF","points-earned":"0"},{"position":"NC","car-driven":"Spyker Ferrari","drivers-number":"21","drivers-name":"Sakon Yamamoto","laps":"2","final-time":"DNF","points-earned":"0"},{"position":"NC","car-driven":"Renault","drivers-number":"3","drivers-name":"Giancarlo Fisichella","laps":"2","final-time":"DNF","points-earned":"0"}]}]}}